pyvalidx/__init__.py
pyvalidx/core.py
pyvalidx/date.py
pyvalidx/exception.py
pyvalidx/fields.py
pyvalidx/model.py
pyvalidx/numeric.py
pyvalidx/py.typed
pyvalidx/string.py
pyvalidx/types.py
pyvalidx-0.1.4.dist-info/licenses/LICENSE
pyvalidx-0.1.4.dist-info/METADATA
pyvalidx-0.1.4.dist-info/WHEEL
pyvalidx-0.1.4.dist-info/top_level.txt
pyvalidx-0.1.4.dist-info/RECORD
