Metadata-Version: 2.4
Name: pyvalidx
Version: 0.1.4
Summary: Custom field validation
Author-email: Harrison Alonso Arroyave Gaviria <harrisonarroyaveg@gmail.com>
Maintainer-email: Harrison Alonso Arroyave Gaviria <harrisonarroyaveg@gmail.com>
License-Expression: MIT
Project-URL: Homepage, https://github.com/harrison-gaviria/pyvalidx
Project-URL: Documentation, https://harrison-gaviria.github.io/pyvalidx/
Project-URL: Repository, https://github.com/harrison-gaviria/pyvalidx
Project-URL: Bug Tracker, https://github.com/harrison-gaviria/pyvalidx/issues
Keywords: validation,pydantic,forms,data-validation,python
Classifier: Development Status :: 4 - Beta
Classifier: Intended Audience :: Developers
Classifier: Operating System :: OS Independent
Classifier: Programming Language :: Python :: 3
Classifier: Programming Language :: Python :: 3.10
Classifier: Programming Language :: Python :: 3.11
Classifier: Programming Language :: Python :: 3.12
Classifier: Programming Language :: Python :: 3.13
Classifier: Topic :: Software Development :: Libraries :: Python Modules
Classifier: Topic :: Internet :: WWW/HTTP :: Dynamic Content
Classifier: Topic :: Software Development :: Libraries
Classifier: Typing :: Typed
Requires-Python: >=3.10
License-File: LICENSE
Requires-Dist: pydantic>=2.11.7
Dynamic: license-file
